<?xml version="1.0" encoding="UTF-8"?>
<page model="com.softwareag.cis.editor.NewFileModel5" translationreference="CIS_EDIT" popupwidth="500" popupheight="290" darkbackground="true">
    <pagebody horizdist="false" takefullheight="true" paddingtop="10">
        <rowarea foldable="false" height="100%" withleftborder="false" withtopborder="false" withrightborder="false">
            <vdist height="2">
            </vdist>
            <itr>
                <label textid="newfileName" width="100">
                </label>
                <field valueprop="fileName" width="200">
                </field>
            </itr>
            <vdist height="10">
            </vdist>
            <rowscrollarea takefullwidth="true" takefullheight="true" hscroll="scroll">
                <iconlist iconlistprop="iconList" vertical="false" cellspacing="5" align="left">
                </iconlist>
                <vdist height="10">
                </vdist>
            </rowscrollarea>
        </rowarea>
        <tabstrip2 tabstripprop="groupTab" align="left" scrollable="true">
        </tabstrip2>
    </pagebody>
    <statusbar>
    </statusbar>
</page>
